zephyr_shell/__about__.py
zephyr_shell/__init__.py
zephyr_shell/__main__.py
zephyr_shell-0.0.1.dist-info/METADATA
zephyr_shell-0.0.1.dist-info/WHEEL
zephyr_shell-0.0.1.dist-info/entry_points.txt
zephyr_shell-0.0.1.dist-info/licenses/LICENSE
zephyr_shell-0.0.1.dist-info/RECORD
