Metadata-Version: 2.4
Name: zephyr-shell
Version: 0.0.1
Summary: The Zephyr Shell
Project-URL: repository, https://github.com/ksachdeva/zephyr-shell
Author: Sachdeva, Kapil
License-File: LICENSE
Classifier: Intended Audience :: Developers
Classifier: License :: OSI Approved :: Apache Software License
Classifier: Operating System :: OS Independent
Classifier: Programming Language :: Python
Classifier: Programming Language :: Python :: 3
Classifier: Programming Language :: Python :: 3.11
Classifier: Programming Language :: Python :: 3.12
Classifier: Programming Language :: Python :: 3.13
Classifier: Programming Language :: Python :: 3.14
Classifier: Topic :: Software Development :: Libraries :: Python Modules
Requires-Python: >=3.11
Requires-Dist: typer>=0.16.0
